redis_py_cluster_meiqia-1.3.2a0.dist-info/DESCRIPTION.rst
redis_py_cluster_meiqia-1.3.2a0.dist-info/METADATA
redis_py_cluster_meiqia-1.3.2a0.dist-info/RECORD
redis_py_cluster_meiqia-1.3.2a0.dist-info/WHEEL
redis_py_cluster_meiqia-1.3.2a0.dist-info/metadata.json
redis_py_cluster_meiqia-1.3.2a0.dist-info/top_level.txt
rediscluster/__init__.py
rediscluster/client.py
rediscluster/connection.py
rediscluster/crc.py
rediscluster/exceptions.py
rediscluster/nodemanager.py
rediscluster/pipeline.py
rediscluster/pubsub.py
rediscluster/utils.py
