Metadata-Version: 2.0
Name: redis-py-cluster-meiqia
Version: 1.3.2a0
Summary: Cluster library for redis 3.0.0 built on top of redis-py lib
Home-page: http://github.com/grokzen/redis-py-cluster
Author: Johan Andersson
Author-email: Grokzen@gmail.com
License: MIT
Keywords: redis,redis cluster
Platform: UNKNOWN
Classifier: Development Status :: 5 - Production/Stable
Classifier: Programming Language :: Python
Classifier: Programming Language :: Python :: 2
Classifier: Programming Language :: Python :: 2.7
Classifier: Programming Language :: Python :: 3
Classifier: Programming Language :: Python :: 3.3
Classifier: Programming Language :: Python :: 3.4
Classifier: Programming Language :: Python :: 3.5
Classifier: Environment :: Web Environment
Classifier: Operating System :: POSIX
Classifier: License :: OSI Approved :: MIT License
Requires-Dist: redis (>=2.10.2)
